resid/__init__.py
resid/document.py
resid/exceptions.py
resid/file.py
resid/file_memory.py
resid/filepath.py
resid/highlevel.py
resid/master.py
resid/pathmod.py
resid/resource.py
resid/urlmod.py
resid/webpage.py
resid/weburl.py
resid-0.0.3.dist-info/LICENSE
resid-0.0.3.dist-info/METADATA
resid-0.0.3.dist-info/WHEEL
resid-0.0.3.dist-info/top_level.txt
resid-0.0.3.dist-info/RECORD
