Metadata-Version: 2.1
Name: resid
Version: 0.0.3
Summary: Analyses resources identifiers to extract valuable information
Home-page: https://github.com/sekgobela-kevin/resid
Author: Sekgobela Kevin
Author-email: kevinnoko23@gmail.com
Project-URL: Bug Tracker, https://github.com/sekgobela-kevin/resid/issues
Keywords: identifier,resource,url
Classifier: Intended Audience :: Developers
Classifier: Development Status :: 2 - Pre-Alpha
Classifier: Programming Language :: Python
Classifier: Programming Language :: Python :: 3
Classifier: Topic :: Software Development :: Libraries
Classifier: Topic :: Software Development :: Libraries :: Python Modules
Requires-Python: >=3.6
License-File: LICENSE
